ci/requirements-upstream-dev.txt
docs/Makefile
docs/api_reference.md
docs/conf.py
docs/contributing.md
docs/ecosystem.md
docs/index.md
docs/make.bat
docs/requirements.txt
docs/_static/pangeo-forge-logo-blue.png
docs/advanced/globus.md
docs/advanced/index.md
docs/composition/file_patterns.md
docs/composition/index.md
docs/composition/styles.md
docs/composition/transforms.md
docs/composition/examples/gpcp-from-gcs.md
docs/composition/examples/index.md
docs/composition/examples/noaa-oisst.md
docs/deployment/action.md
docs/deployment/cli.md
docs/deployment/example-feedstocks.md
docs/deployment/feedstocks.md
docs/deployment/index.md
docs/getting_started/index.md
docs/getting_started/installation.md
examples/feedstock/gpcp_from_gcs.py
examples/feedstock/gpcp_from_gcs_dynamic_chunks.py
examples/feedstock/hrrr_kerchunk_concat_step.py
examples/feedstock/hrrr_kerchunk_concat_valid_time.py
examples/feedstock/meta.yaml
examples/feedstock/narr_opendap.py
examples/feedstock/noaa_oisst.py
examples/feedstock/terraclimate.py
examples/runner-commands/bake.sh
examples/runner-config/local.json
examples/runner-config/local.py
examples/runner-config/s3.json
pangeo_forge_recipes/README.md
pangeo_forge_recipes/__init__.py
pangeo_forge_recipes/_version.py
pangeo_forge_recipes/aggregation.py
pangeo_forge_recipes/chunk_grid.py
pangeo_forge_recipes/combiners.py
pangeo_forge_recipes/injections.py
pangeo_forge_recipes/openers.py
pangeo_forge_recipes/patterns.py
pangeo_forge_recipes/py.typed
pangeo_forge_recipes/rechunking.py
pangeo_forge_recipes/serialization.py
pangeo_forge_recipes/storage.py
pangeo_forge_recipes/transforms.py
pangeo_forge_recipes/types.py
pangeo_forge_recipes/utils.py
pangeo_forge_recipes/writers.py
tests/__init__.py
tests/conftest.py
tests/data_generation.py
tests/http_auth_server.py
tests/test_aggregation.py
tests/test_chunk_grid.py
tests/test_combiners.py
tests/test_end_to_end.py
tests/test_integration.py
tests/test_openers.py
tests/test_patterns.py
pangeo_forge_recipes-0.10.8.dist-info/LICENSE
pangeo_forge_recipes-0.10.8.dist-info/METADATA
pangeo_forge_recipes-0.10.8.dist-info/WHEEL
pangeo_forge_recipes-0.10.8.dist-info/entry_points.txt
pangeo_forge_recipes-0.10.8.dist-info/top_level.txt
pangeo_forge_recipes-0.10.8.dist-info/RECORD
