Metadata-Version: 2.1
Name: pangeo-forge-recipes
Version: 0.10.8
Summary: Pipeline tools for building and publishing analysis ready datasets.
Author-email: Ryan Abernathey <rpa@ldeo.columbia.edu>
License: Apache-2.0
Project-URL: Homepage, https://github.com/pangeo-forge/pangeo-forge-recipes
Project-URL: Tracker, https://github.com/pangeo-forge/pangeo-forge-recipes/issues
Project-URL: Documentation, https://pangeo-forge.readthedocs.io/en/latest/
Keywords: pangeo,data
Classifier: Development Status :: 1 - Planning
Classifier: License :: OSI Approved :: Apache Software License
Classifier: Operating System :: OS Independent
Classifier: Intended Audience :: Science/Research
Classifier: Programming Language :: Python
Classifier: Programming Language :: Python :: 3
Classifier: Programming Language :: Python :: 3.8
Classifier: Programming Language :: Python :: 3.9
Classifier: Topic :: Scientific/Engineering
Requires-Python: >=3.8
License-File: LICENSE
Requires-Dist: apache-beam
Requires-Dist: cftime
Requires-Dist: dask>=2021.11.2
Requires-Dist: fastparquet
Requires-Dist: fsspec[http]>=2023.4.0
Requires-Dist: h5netcdf
Requires-Dist: h5py>=3.3.0
Requires-Dist: kerchunk>=0.0.7
Requires-Dist: netcdf4
Requires-Dist: numcodecs>=0.9.0
Requires-Dist: xarray>=0.18.0
Requires-Dist: zarr>=2.12.0
Provides-Extra: minio
Requires-Dist: docker; extra == "minio"
Provides-Extra: test
Requires-Dist: click; extra == "test"
Requires-Dist: pytest<8.0.0; extra == "test"
Requires-Dist: pytest-cov; extra == "test"
Requires-Dist: pytest-xdist; extra == "test"
Requires-Dist: pytest-lazy-fixture; extra == "test"
Requires-Dist: pytest-sugar; extra == "test"
Requires-Dist: pytest-timeout; extra == "test"
Requires-Dist: s3fs; extra == "test"
Requires-Dist: gcsfs; extra == "test"
Requires-Dist: scipy; extra == "test"
